Assignment-1-Banana-Problem/Light.v
module light_controller (
    input A,
    input B,
    input C,
    output light
);

wire nA, nB, nC;
wire term1, term2, term3, term4;

assign nA = ~A;
assign nB = ~B;
assign nC = ~C;

assign term1 = nA & nB & nC;  
assign term2 = nA & B & C;    
assign term3 = A & nB & C;    
assign term4 = A & B & nC;   

assign light = term1 | term2 | term3 | term4;  

endmodule

Assignment-1-Banana-Problem/light-tb.v
module testbench;

reg A, B, C;
wire light;

light_controller uut (
    .A(A),
    .B(B),
    .C(C),
    .light(light)
);

initial begin
    // Display headers
    $display("A B C | LIGHT");
    $display("---------");

    // Test all combinations of inputs
    A = 0; B = 0; C = 0; #10;
    $display("%b %b %b | %b", A, B, C, light);

    A = 0; B = 0; C = 1; #10;
    $display("%b %b %b | %b", A, B, C, light);

    A = 0; B = 1; C = 0; #10;
    $display("%b %b %b | %b", A, B, C, light);

    A = 0; B = 1; C = 1; #10;
    $display("%b %b %b | %b", A, B, C, light);

    A = 1; B = 0; C = 0; #10;
    $display("%b %b %b | %b", A, B, C, light);

    A = 1; B = 0; C = 1; #10;
    $display("%b %b %b | %b", A, B, C, light);

    A = 1; B = 1; C = 0; #10;
    $display("%b %b %b | %b", A, B, C, light);

    A = 1; B = 1; C = 1; #10;
    $display("%b %b %b | %b", A, B, C, light);

    A = 0; B = 0; C = 0; #10;
    $display("%b %b %b | %b", A, B, C, light);    
    
    $finish;
end

initial begin
    $dumpfile("light-tb.vcd");
    $dumpvars(0, testbench);
end

endmodule

Assignment-1-Banana-Problem/light-tb.vcd
$date
	Tue Oct 01 00:25:23 2024
$end
$version
	Icarus Verilog
$end
$timescale
	1s
$end
$scope module testbench $end
$var wire 1 ! light $end
$var reg 1 " A $end
$var reg 1 # B $end
$var reg 1 $ C $end
$scope module uut $end
$var wire 1 " A $end
$var wire 1 # B $end
$var wire 1 $ C $end
$var wire 1 ! light $end
$var wire 1 % nA $end
$var wire 1 & nB $end
$var wire 1 ' nC $end
$var wire 1 ( term1 $end
$var wire 1 ) term2 $end
$var wire 1 * term3 $end
$var wire 1 + term4 $end
$upscope $end
$upscope $end
$enddefinitions $end
$comment Show the parameter values. $end
$dumpall
$end
#0
$dumpvars
0+
0*
0)
1(
1'
1&
1%
0$
0#
0"
1!
$end
#10
0!
0(
0'
1$
#20
1'
0&
0$
1#
#30
1!
0'
1)
1$
#40
0!
1'
0)
1&
0%
0$
0#
1"
#50
1!
0'
1*
1$
#60
1+
1'
0*
0&
0$
1#
#70
0!
0+
0'
1$
#80
1!
1(
1'
1&
1%
0$
0#
0"
