week3/Q6/circ6.v
module full_adder (
    input A, B, Cin,
    output Sum, Cout
);
    assign Sum = A ^ B ^ Cin;
    assign Cout = (A & B) | (B & Cin) | (A & Cin);
endmodule

module two_full_adders (
    input [2:0] i1,
    input i2,
    output Sum1, Cout1
);
wire Sum0, Cout0;

full_adder FA0 (
	.A(i1[0]),
	.B(i1[1]),
	.Cin(i1[2]),
	.Sum(Sum0),
	.Cout(Cout0)
);

full_adder FA1 (
	.A(Sum0),
	.B(i2),
	.Cin(Cout0),
	.Sum(Sum1),
	.Cout(Cout1)
);
endmodule

week3/Q6/circ6_test.v
module cir6test;
reg [2:0] i1;
reg i2;
wire Sum1, Cout1;

two_full_adders UUT (
.i1(i1),
.i2(i2),
.Sum1(Sum1),
.Cout1(Cout1)
);

initial
begin

{i1, i2} = 4'b0000; #10;
{i1, i2} = 4'b0001; #10;
{i1, i2} = 4'b0010; #10;
{i1, i2} = 4'b0011; #10;
{i1, i2} = 4'b0100; #10;
{i1, i2} = 4'b0101; #10;
{i1, i2} = 4'b0110; #10;
{i1, i2} = 4'b0111; #10;
{i1, i2} = 4'b1000; #10;
{i1, i2} = 4'b1001; #10;
{i1, i2} = 4'b1010; #10;
{i1, i2} = 4'b1011; #10;
{i1, i2} = 4'b1100; #10;
{i1, i2} = 4'b1101; #10;
{i1, i2} = 4'b1110; #10;
{i1, i2} = 4'b1111; #10;
{i1, i2} = 4'b0000; #10;


end

initial
begin
 $monitor($time, " i1=%b, i2=%b, Sum1=%b, Cout1=%b", i1, i2, Sum1, Cout1);end
initial
begin

$dumpfile("circ6.vcd");
$dumpvars(0, cir6test);
end
endmodule

week3/Q6/circ6.vcd
$date
	Fri Aug 30 23:03:05 2024
$end
$version
	Icarus Verilog
$end
$timescale
	1s
$end
$scope module cir6test $end
$var wire 1 ! Sum1 $end
$var wire 1 " Cout1 $end
$var reg 3 # i1 [2:0] $end
$var reg 1 $ i2 $end
$scope module UUT $end
$var wire 3 % i1 [2:0] $end
$var wire 1 $ i2 $end
$var wire 1 ! Sum1 $end
$var wire 1 & Sum0 $end
$var wire 1 " Cout1 $end
$var wire 1 ' Cout0 $end
$scope module FA0 $end
$var wire 1 ( A $end
$var wire 1 ) B $end
$var wire 1 * Cin $end
$var wire 1 ' Cout $end
$var wire 1 & Sum $end
$upscope $end
$scope module FA1 $end
$var wire 1 & A $end
$var wire 1 $ B $end
$var wire 1 ' Cin $end
$var wire 1 " Cout $end
$var wire 1 ! Sum $end
$upscope $end
$upscope $end
$upscope $end
$enddefinitions $end
$comment Show the parameter values. $end
$dumpall
$end
#0
$dumpvars
0*
0)
0(
0'
0&
b0 %
0$
b0 #
0"
0!
$end
#10
1!
1$
#20
1&
1!
1(
b1 #
b1 %
0$
#30
1"
0!
1$
#40
0"
1!
0(
1)
b10 #
b10 %
0$
#50
1"
0!
1$
#60
1'
0&
0"
1!
1(
b11 #
b11 %
0$
#70
1"
0!
1$
#80
0'
0"
1&
1!
0(
0)
1*
b100 #
b100 %
0$
#90
1"
0!
1$
#100
0&
1'
0"
1!
1(
b101 #
b101 %
0$
#110
1"
0!
1$
#120
0"
1!
0(
1)
b110 #
b110 %
0$
#130
1"
0!
1$
#140
1&
1"
0!
1(
b111 #
b111 %
0$
#150
1!
1$
#160
0"
0'
0&
0!
0(
0)
0*
b0 #
b0 %
0$
