week5/reg_file.v
// 2 16-bit register file with read and write functionality

module reg_file (
    input wire clk,
    input wire reset,
    input wire wr,
    input wire [2:0] rd_addr_a, rd_addr_b, wr_addr,
    input wire [15:0] d_in,
    output reg [15:0] d_out_a, d_out_b
);

    reg [15:0] reg_array [7:0];

    always @(posedge clk) begin
        if (reset) begin
            reg_array[0] <= 16'h0000;
            reg_array[1] <= 16'h0000;
            reg_array[2] <= 16'h0000;
            reg_array[3] <= 16'h0000;
            reg_array[4] <= 16'h0000;
            reg_array[5] <= 16'h0000;
            reg_array[6] <= 16'h0000;
            reg_array[7] <= 16'h0000;
        end else if (wr) begin
            reg_array[wr_addr] <= d_in;
        end
    end

    always @(*) begin
        d_out_a = reg_array[rd_addr_a];
        d_out_b = reg_array[rd_addr_b];
    end
endmodule

week5/register-tb.v
module reg_file_tb;

  reg clk, reset, wr;
  reg [2:0] rd_addr_a, rd_addr_b, wr_addr;
  reg [15:0] d_in;
  wire [15:0] d_out_a, d_out_b;

  reg_file uut (
    .clk(clk),
    .reset(reset),
    .wr(wr),
    .rd_addr_a(rd_addr_a),
    .rd_addr_b(rd_addr_b),
    .wr_addr(wr_addr),
    .d_in(d_in),
    .d_out_a(d_out_a),
    .d_out_b(d_out_b)
  );

  always #10 clk = ~clk;

  initial begin
    clk = 0;
    reset = 0;
    wr = 0;
    rd_addr_a = 3'b000;
    rd_addr_b = 3'b001;
    wr_addr = 3'b000;
    d_in = 16'h0000;

    $dumpfile("reg_file_tb.vcd");
    $dumpvars(0, reg_file_tb);

    reset = 1; 
    #40;
    reset = 0; 

    wr = 1; 
    d_in = 16'h1234; 
    wr_addr = 3'b000; 
    #40;

    d_in = 16'h5678; 
    wr_addr = 3'b001; 
    #40;

    wr = 0; 
    rd_addr_a = 3'b000; 
    rd_addr_b = 3'b001; 
    #40;

    $display("Read from reg 0: %h, Read from reg 1: %h", d_out_a, d_out_b);

    wr = 1; 
    d_in = 16'h9ABC; 
    wr_addr = 3'b010; 
    #40;

    wr = 0; 
    rd_addr_a = 3'b000; 
    rd_addr_b = 3'b010; 
    #40;

    $display("Read from reg 0: %h, Read from reg 2: %h", d_out_a, d_out_b);

    wr = 1; 
    d_in = 16'hDEF0; 
    wr_addr = 3'b000; 
    #40;

    wr = 0; 
    rd_addr_a = 3'b000; 
    #40;

    $display("Read from reg 0 after overwrite: %h", d_out_a);

    $finish;
  end

endmodule

week5/reg_file_tb.vcd
$date
	Sun Oct 06 12:50:35 2024
$end
$version
	Icarus Verilog
$end
$timescale
	1s
$end
$scope module reg_file_tb $end
$var wire 16 ! d_out_b [15:0] $end
$var wire 16 " d_out_a [15:0] $end
$var reg 1 # clk $end
$var reg 16 $ d_in [15:0] $end
$var reg 3 % rd_addr_a [2:0] $end
$var reg 3 & rd_addr_b [2:0] $end
$var reg 1 ' reset $end
$var reg 1 ( wr $end
$var reg 3 ) wr_addr [2:0] $end
$scope module uut $end
$var wire 1 # clk $end
$var wire 16 * d_in [15:0] $end
$var wire 3 + rd_addr_a [2:0] $end
$var wire 3 , rd_addr_b [2:0] $end
$var wire 1 ' reset $end
$var wire 1 ( wr $end
$var wire 3 - wr_addr [2:0] $end
$var reg 16 . d_out_a [15:0] $end
$var reg 16 / d_out_b [15:0] $end
$upscope $end
$upscope $end
$enddefinitions $end
$comment Show the parameter values. $end
$dumpall
$end
#0
$dumpvars
bx /
bx .
b0 -
b1 ,
b0 +
b0 *
b0 )
0(
1'
b1 &
b0 %
b0 $
0#
bx "
bx !
$end
#10
b0 !
b0 /
b0 "
b0 .
1#
#20
0#
#30
1#
#40
0#
b1001000110100 $
b1001000110100 *
1(
0'
#50
b1001000110100 "
b1001000110100 .
1#
#60
0#
#70
1#
#80
0#
b1 )
b1 -
b101011001111000 $
b101011001111000 *
#90
b101011001111000 !
b101011001111000 /
1#
#100
0#
#110
1#
#120
0#
0(
#130
1#
#140
0#
#150
1#
#160
0#
b10 )
b10 -
b1001101010111100 $
b1001101010111100 *
1(
#170
1#
#180
0#
#190
1#
#200
b1001101010111100 !
b1001101010111100 /
0#
b10 &
b10 ,
0(
#210
1#
#220
0#
#230
1#
#240
0#
b0 )
b0 -
b1101111011110000 $
b1101111011110000 *
1(
#250
b1101111011110000 "
b1101111011110000 .
1#
#260
0#
#270
1#
#280
0#
0(
